PyNetworkD3/__init__.py
PyNetworkD3/constants.py
PyNetworkD3/core.py
PyNetworkD3/kws.py
PyNetworkD3/templates/adjacency matrix/code.js
PyNetworkD3/templates/adjacency matrix/style.css
PyNetworkD3/templates/arc diagram/code.js
PyNetworkD3/templates/arc diagram/style.css
PyNetworkD3/templates/export_main.html
PyNetworkD3/templates/force graph/code-canvas.js
PyNetworkD3/templates/force graph/code-svg.js
PyNetworkD3/templates/force graph/code.js
PyNetworkD3/templates/force graph/style.css
PyNetworkD3/templates/js utils/color function.js
PyNetworkD3/templates/js utils/size function.js
PyNetworkD3/templates/main.html
PyNetworkD3/templates/main.js
PyNetworkD3/templates/radial diagram/code.js
PyNetworkD3/templates/radial diagram/style.css
PyNetworkD3/utils.py
pynetworkd3-0.0.9.dist-info/entry_points.txt
pynetworkd3-0.0.9.dist-info/LICENSE
pynetworkd3-0.0.9.dist-info/WHEEL
pynetworkd3-0.0.9.dist-info/METADATA
pynetworkd3-0.0.9.dist-info/RECORD
