Metadata-Version: 2.1
Name: pynetworkd3
Version: 0.0.9
Summary: Create D3 visualization networks with Python
Home-page: https://github.com/Hernan4444/PyNetworkD3
License: MIT
Author: Hernán Valdivieso
Author-email: hfvaldivieso@uc.cl
Maintainer: Hernán Valdivieso
Maintainer-email: hfvaldivieso@uc.cl
Requires-Python: >=3.6,<4.0
Classifier: License :: OSI Approved :: MIT License
Classifier: Programming Language :: Python :: 3
Classifier: Programming Language :: Python :: 3.10
Classifier: Programming Language :: Python :: 3.6
Classifier: Programming Language :: Python :: 3.7
Classifier: Programming Language :: Python :: 3.8
Classifier: Programming Language :: Python :: 3.9
Requires-Dist: pyserial (>=3.5,<4.0)
Project-URL: Documentation, https://github.com/Hernan4444/PyNetworkD3#readme
Project-URL: Issue Tracker, https://github.com/Hernan4444/PyNetworkD3/issues
Project-URL: Repository, https://github.com/Hernan4444/PyNetworkD3
